Metadata-Version: 2.3
Name: course2025lesson1example
Version: 0.1.2
Summary: 
Author: Akella101
Author-email: eekosyanenko@yandex.ru
Requires-Python: >=3.12
Classifier: Programming Language :: Python :: 3
Classifier: Programming Language :: Python :: 3.12
Classifier: Programming Language :: Python :: 3.13
Requires-Dist: pyyaml (>=6.0.2,<7.0.0)
Requires-Dist: requests (>=2.32.4,<3.0.0)
